[
    {
        "name": "B9_Aero_Wing_Procedural_TypeA",
        "title": "B9 Procedural Wing (Spaceplane)",
        "description": "Rated for LEO reentries.",
        "mod": "B9 Procedural Wings",
        "cost": "0",
        "entry_cost": "15000",
        "category": "SPACEPLANES",
        "info": "Wing",
        "year": "1960",
        "technology": "hypersonicFlightRP0",
        "era": "02-SAT",
        "ro": true,
        "rp0": true,
        "orphan": false,
        "rp0_conf": true,
        "spacecraft": "X-15",
        "engine_config": "",
        "upgrade": false,
        "entry_cost_mods": "wingsSpaceplane",
        "identical_part_name": "",
        "module_tags": []
    },
    {
        "name": "B9_Aero_Wing_Procedural_TypeB",
        "title": "B9 Procedural Control Surface (Spaceplane)",
        "description": "Rated for LEO reentries.",
        "mod": "B9 Procedural Wings",
        "cost": "0",
        "entry_cost": "15000",
        "category": "SPACEPLANES",
        "info": "Control Surface",
        "year": "1960",
        "technology": "hypersonicFlightRP0",
        "era": "02-SAT",
        "ro": true,
        "rp0": true,
        "orphan": false,
        "rp0_conf": true,
        "spacecraft": "X-15",
        "engine_config": "",
        "upgrade": false,
        "entry_cost_mods": "wingsSpaceplane",
        "identical_part_name": "",
        "module_tags": []
    },
    {
        "name": "B9_Aero_Wing_Procedural_TypeC",
        "title": "B9 Procedural Wing, All-Moving (Spaceplane)",
        "description": "Rated for LEO reentries.",
        "mod": "B9 Procedural Wings",
        "cost": "0",
        "entry_cost": "15000",
        "category": "SPACEPLANES",
        "info": "Wing",
        "year": "1960",
        "technology": "hypersonicFlightRP0",
        "era": "02-SAT",
        "ro": true,
        "rp0": true,
        "orphan": false,
        "rp0_conf": true,
        "spacecraft": "X-15",
        "engine_config": "",
        "upgrade": false,
        "entry_cost_mods": "wingsSpaceplane",
        "identical_part_name": "",
        "module_tags": []
    },
    {
        "name": "RO-B9ProcAMWing-Early",
        "title": "B9 Procedural Wing, All-Moving (Early)",
        "description": "Rated for Mach 1 flight and below.",
        "mod": "B9 Procedural Wings",
        "cost": "0",
        "entry_cost": "1",
        "category": "FLIGHT",
        "info": "",
        "year": "0",
        "technology": "unlockParts",
        "era": "00-START",
        "ro": true,
        "rp0": true,
        "orphan": false,
        "rp0_conf": true,
        "spacecraft": "",
        "engine_config": "",
        "upgrade": false,
        "entry_cost_mods": "1",
        "identical_part_name": "",
        "module_tags": []
    },
    {
        "name": "RO-B9ProcAMWing-Supersonic",
        "title": "B9 Procedural Wing, All-Moving (Supersonic)",
        "description": "Rated for Mach 3 flight.",
        "mod": "B9 Procedural Wings",
        "cost": "0",
        "entry_cost": "10000",
        "category": "FLIGHT",
        "info": "Wing",
        "year": "PW",
        "technology": "supersonicDev",
        "era": "01-PW",
        "ro": true,
        "rp0": true,
        "orphan": false,
        "rp0_conf": true,
        "spacecraft": "",
        "engine_config": "",
        "upgrade": false,
        "entry_cost_mods": "wingsSupersonic",
        "identical_part_name": "",
        "module_tags": []
    },
    {
        "name": "RO-B9ProcCS-Early",
        "title": "B9 Procedural Control Surface (Early)",
        "description": "Rated for Mach 1 flight and below.",
        "mod": "B9 Procedural Wings",
        "cost": "0",
        "entry_cost": "1",
        "category": "FLIGHT",
        "info": "",
        "year": "0",
        "technology": "unlockParts",
        "era": "00-START",
        "ro": true,
        "rp0": true,
        "orphan": false,
        "rp0_conf": true,
        "spacecraft": "",
        "engine_config": "",
        "upgrade": false,
        "entry_cost_mods": "1",
        "identical_part_name": "",
        "module_tags": []
    },
    {
        "name": "RO-B9ProcCS-Supersonic",
        "title": "B9 Procedural Control Surface (Supersonic)",
        "description": "Rated for Mach 3 flight.",
        "mod": "B9 Procedural Wings",
        "cost": "0",
        "entry_cost": "10000",
        "category": "FLIGHT",
        "info": "Control Surface",
        "year": "PW",
        "technology": "supersonicDev",
        "era": "01-PW",
        "ro": true,
        "rp0": true,
        "orphan": false,
        "rp0_conf": true,
        "spacecraft": "",
        "engine_config": "",
        "upgrade": false,
        "entry_cost_mods": "wingsSupersonic",
        "identical_part_name": "",
        "module_tags": []
    },
    {
        "name": "RO-B9ProcWing-Early",
        "title": "B9 Procedural Wing (Early)",
        "description": "Rated for Mach 1 flight and below.",
        "mod": "B9 Procedural Wings",
        "cost": "0",
        "entry_cost": "1",
        "category": "FLIGHT",
        "info": "",
        "year": "0",
        "technology": "unlockParts",
        "era": "00-START",
        "ro": true,
        "rp0": true,
        "orphan": false,
        "rp0_conf": true,
        "spacecraft": "",
        "engine_config": "",
        "upgrade": false,
        "entry_cost_mods": "1",
        "identical_part_name": "",
        "module_tags": []
    },
    {
        "name": "RO-B9ProcWing-Supersonic",
        "title": "B9 Procedural Wing (Supersonic)",
        "description": "Rated for Mach 3 flight.",
        "mod": "B9 Procedural Wings",
        "cost": "0",
        "entry_cost": "10000",
        "category": "FLIGHT",
        "info": "Wing",
        "year": "PW",
        "technology": "supersonicDev",
        "era": "01-PW",
        "ro": true,
        "rp0": true,
        "orphan": false,
        "rp0_conf": true,
        "spacecraft": "",
        "engine_config": "",
        "upgrade": false,
        "entry_cost_mods": "wingsSupersonic",
        "identical_part_name": "",
        "module_tags": []
    }
]