[
    {
        "name": "KAS_CPort1",
        "title": "KAS/KIS - Connector Port",
        "description": "A multi-purpose port. Can be used to plug a winch connector or for building pipes. Useful for making ground bases and transferring resources.",
        "mod": "KAS",
        "cost": "100",
        "entry_cost": "2000",
        "category": "MATERIALS",
        "info": "KAS",
        "year": "1967",
        "technology": "materialsScienceLunar",
        "era": "05-LUNAR",
        "ro": true,
        "rp0": true,
        "orphan": false,
        "rp0_conf": true,
        "spacecraft": "",
        "engine_config": "",
        "upgrade": false,
        "entry_cost_mods": "",
        "identical_part_name": "",
        "module_tags": []
    },
    {
        "name": "KAS_Hook_Anchor",
        "title": "KAS/KIS - Anchor",
        "description": "An anchor to be used for boat, airship or everything else. In addition to its weight, it also provide drag and friction when touching the ground.",
        "mod": "KAS",
        "cost": "100",
        "entry_cost": "2000",
        "category": "MATERIALS",
        "info": "KAS",
        "year": "1964",
        "technology": "materialsScienceAdvCapsules",
        "era": "04-ADV",
        "ro": true,
        "rp0": true,
        "orphan": false,
        "rp0_conf": true,
        "spacecraft": "",
        "engine_config": "",
        "upgrade": false,
        "entry_cost_mods": "",
        "identical_part_name": "",
        "module_tags": []
    },
    {
        "name": "KAS_Hook_GrapplingHook",
        "title": "KAS/KIS - Grappling Hook",
        "description": "This hook will attach to everything it collides with, as long as the impact is strong enough. Can be mounted on a winch. To be used with the winch eject function.",
        "mod": "KAS",
        "cost": "850",
        "entry_cost": "8500",
        "category": "MATERIALS",
        "info": "KAS",
        "year": "1972",
        "technology": "materialsScienceSpaceStation",
        "era": "06-STATION",
        "ro": true,
        "rp0": false,
        "orphan": false,
        "rp0_conf": false,
        "spacecraft": "",
        "engine_config": "",
        "upgrade": false,
        "entry_cost_mods": "",
        "identical_part_name": "",
        "module_tags": []
    },
    {
        "name": "KAS_Hook_Harpoon",
        "title": "KAS/KIS - Harpoon",
        "description": "This hook will attach to everything it collides with, as long as the impact is strong enough. Can be mounted on a winch. To be used with the winch eject function.",
        "mod": "KAS",
        "cost": "100",
        "entry_cost": "2000",
        "category": "MATERIALS",
        "info": "KAS",
        "year": "1964",
        "technology": "materialsScienceAdvCapsules",
        "era": "04-ADV",
        "ro": true,
        "rp0": true,
        "orphan": false,
        "rp0_conf": true,
        "spacecraft": "",
        "engine_config": "",
        "upgrade": false,
        "entry_cost_mods": "",
        "identical_part_name": "",
        "module_tags": []
    },
    {
        "name": "KAS_Hook_Magnet",
        "title": "KAS/KIS - Electro-Magnet",
        "description": "This electro-magnet is perfect for grabing heavy objects without a connector or a docking port. Can be mounted on a winch or on a hook support.",
        "mod": "KAS",
        "cost": "100",
        "entry_cost": "2000",
        "category": "MATERIALS",
        "info": "KAS",
        "year": "1964",
        "technology": "materialsScienceAdvCapsules",
        "era": "04-ADV",
        "ro": true,
        "rp0": true,
        "orphan": false,
        "rp0_conf": true,
        "spacecraft": "",
        "engine_config": "",
        "upgrade": false,
        "entry_cost_mods": "",
        "identical_part_name": "",
        "module_tags": []
    },
    {
        "name": "KAS_Pylon1",
        "title": "KAS/KIS - Pylon",
        "description": "A simple part that can be used as a support for attaching stuff (ports, pipes, etc...)",
        "mod": "KAS",
        "cost": "20",
        "entry_cost": "400",
        "category": "MATERIALS",
        "info": "KAS",
        "year": "1952",
        "technology": "earlyMaterialsScience",
        "era": "01-PW",
        "ro": true,
        "rp0": true,
        "orphan": false,
        "rp0_conf": true,
        "spacecraft": "",
        "engine_config": "",
        "upgrade": false,
        "entry_cost_mods": "",
        "identical_part_name": "",
        "module_tags": []
    },
    {
        "name": "KAS_Strut1",
        "title": "KAS/KIS - Strut",
        "description": "End point for building a strut from EVA. Links are restricted to the same vessel. Useful for strengthening a vessel.",
        "mod": "KAS",
        "cost": "100",
        "entry_cost": "2000",
        "category": "MATERIALS",
        "info": "KAS",
        "year": "1967",
        "technology": "materialsScienceLunar",
        "era": "05-LUNAR",
        "ro": true,
        "rp0": true,
        "orphan": false,
        "rp0_conf": true,
        "spacecraft": "",
        "engine_config": "",
        "upgrade": false,
        "entry_cost_mods": "",
        "identical_part_name": "",
        "module_tags": []
    },
    {
        "name": "KAS_Winch1",
        "title": "KAS/KIS - Winch (Stack)",
        "description": "A winch used to extend and retract a cable. A hook or a connector port can be pre-attached if needed.",
        "mod": "KAS",
        "cost": "900",
        "entry_cost": "5300",
        "category": "MATERIALS",
        "info": "KAS",
        "year": "1964",
        "technology": "materialsScienceAdvCapsules",
        "era": "04-ADV",
        "ro": true,
        "rp0": false,
        "orphan": false,
        "rp0_conf": false,
        "spacecraft": "",
        "engine_config": "",
        "upgrade": false,
        "entry_cost_mods": "",
        "identical_part_name": "",
        "module_tags": []
    },
    {
        "name": "KAS_Winch2",
        "title": "KAS/KIS - Winch (Radial)",
        "description": "A winch used to extend and retract a cable. A hook or a connector port can be pre-attached if needed.",
        "mod": "KAS",
        "cost": "1200",
        "entry_cost": "12200",
        "category": "MATERIALS",
        "info": "KAS",
        "year": "1972",
        "technology": "materialsScienceSpaceStation",
        "era": "06-STATION",
        "ro": true,
        "rp0": false,
        "orphan": false,
        "rp0_conf": false,
        "spacecraft": "",
        "engine_config": "",
        "upgrade": false,
        "entry_cost_mods": "",
        "identical_part_name": "",
        "module_tags": []
    }
]