[
    {
        "name": "SCANsat_Scanner",
        "title": "SCAN RADAR Altimetry Sensor",
        "description": "This radar set can provide low-resolution altimetry data. Best with low altitude orbits.",
        "mod": "SCANsat",
        "cost": "500",
        "entry_cost": "10000",
        "category": "SCIENCE",
        "info": "SCANSat-1",
        "year": "1961",
        "technology": "scienceHuman",
        "era": "03-HUMAN",
        "ro": true,
        "rp0": true,
        "orphan": false,
        "rp0_conf": true,
        "spacecraft": "",
        "engine_config": "",
        "upgrade": false,
        "entry_cost_mods": "",
        "identical_part_name": "",
        "module_tags": [
            "Instruments"
        ]
    },
    {
        "name": "SCANsat_Scanner2",
        "title": "SCAN SAR Altimetry Sensor",
        "description": "This Synthetic Aperture RADAR sensor uses its flight path to simulate a much larger antenna. This makes it possible to detect terrain elevation at much higher resolution. The downside is that its field of view is comparatively small, and it works better at higher altitudes. Min Alt: 10km, Max Alt: 8000km, Best Alt: 7500km, FOV: 2",
        "mod": "SCANsat",
        "cost": "1000",
        "entry_cost": "20000",
        "category": "SCIENCE",
        "info": "SCANSat-3",
        "year": "1972",
        "technology": "deepSpaceScience",
        "era": "06-STATION",
        "ro": true,
        "rp0": true,
        "orphan": false,
        "rp0_conf": true,
        "spacecraft": "",
        "engine_config": "",
        "upgrade": false,
        "entry_cost_mods": "",
        "identical_part_name": "",
        "module_tags": [
            "Instruments"
        ]
    },
    {
        "name": "SCANsat_Scanner24",
        "title": "SCAN Multispectral Sensor",
        "description": "This multichannel sensor detects radiation across several infrared, visible light, and RADAR bands. This gives it the capability to differentiate between terrain types and biomes. It can also detect anomalies such as structures on the ground. Min Alt: 10km, Max Alt: 5000km, Best Alt: 2500km, FOV: 4",
        "mod": "SCANsat",
        "cost": "2000",
        "entry_cost": "40000",
        "category": "SCIENCE",
        "info": "SCANSat-2",
        "year": "1964",
        "technology": "scienceAdvCapsules",
        "era": "04-ADV",
        "ro": true,
        "rp0": true,
        "orphan": false,
        "rp0_conf": true,
        "spacecraft": "",
        "engine_config": "",
        "upgrade": false,
        "entry_cost_mods": "",
        "identical_part_name": "",
        "module_tags": [
            "Instruments"
        ]
    },
    {
        "name": "SCANsat_Scanner32",
        "title": "SCAN Anomaly Scanner",
        "description": "This small sensor can automatically identify nearby anomalies. Since it only works over very short distances and at very low altitudes, it's primarily useful to track identified anomalies that have been visited. Min Alt: 0, Max Alt: 5km, Best Alt: 0, FOV: 1",
        "mod": "SCANsat",
        "cost": "500",
        "entry_cost": "10000",
        "category": "SCIENCE",
        "info": "SCANSat-5",
        "year": "1981",
        "technology": "scienceExploration",
        "era": "07-SPCPLANES",
        "ro": true,
        "rp0": true,
        "orphan": false,
        "rp0_conf": true,
        "spacecraft": "",
        "engine_config": "",
        "upgrade": false,
        "entry_cost_mods": "",
        "identical_part_name": "",
        "module_tags": [
            "Instruments"
        ]
    },
    {
        "name": "SCANsat_Tracker",
        "title": "SCAN MapTraq\u00c3\u201a\u00c2\u00ae",
        "description": "Originally intended for the consumer market, this small device can communicate with a mapping satellite network and display a map and your position on it. Since nobody has actually built such a satellite network, these devices can currently be acquired very cheaply in bulk.",
        "mod": "SCANsat",
        "cost": "500",
        "entry_cost": "10000",
        "category": "SCIENCE",
        "info": "SCANSat-4",
        "year": "1981",
        "technology": "scienceExploration",
        "era": "07-SPCPLANES",
        "ro": true,
        "rp0": true,
        "orphan": false,
        "rp0_conf": true,
        "spacecraft": "",
        "engine_config": "",
        "upgrade": false,
        "entry_cost_mods": "",
        "identical_part_name": "",
        "module_tags": [
            "Instruments"
        ]
    }
]